python_package_creator.py
python_package_creator-0.1.0.dist-info/LICENSE
python_package_creator-0.1.0.dist-info/METADATA
python_package_creator-0.1.0.dist-info/WHEEL
python_package_creator-0.1.0.dist-info/entry_points.txt
python_package_creator-0.1.0.dist-info/RECORD
